{
  "errata_id": "974b283102cf4e820d4ab85d2ae80934c5d58c6b6a5f695ab6a23d5f607d67c4",
  "attachments": [],
  "tags": [
    "book:stax-cmath",
    "assignment-type:reading",
    "blooms:1",
    "time:medium",
    "lo:stax-cmath:06-07-05",
    "context-cnxmod:792218eb-bd49-496b-983a-439f3697e6d0",
    "book-slug:contemporary-mathematics",
    "module-slug:contemporary-mathematics:6-7-investments"
  ],
  "books": [
    {
      "name": "stax-cmath",
      "lo": [
        "06-07-05"
      ]
    }
  ],
  "context": [
    "m00063"
  ]
}