{
  "errata_id": "0c69092d16c56b717cea594037ae9294a4328caa9f99099b6a01bb4907a2928c",
  "attachments": [],
  "tags": [
    "book:stax-cmath",
    "assignment-type:reading",
    "blooms:1",
    "time:medium",
    "lo:stax-cmath:13-01-03",
    "context-cnxmod:91247c69-d5b4-432f-8825-8e17ed9ee042",
    "book-slug:contemporary-mathematics",
    "module-slug:contemporary-mathematics:13-1-math-and-art"
  ],
  "books": [
    {
      "name": "stax-cmath",
      "lo": [
        "13-01-03"
      ]
    }
  ],
  "context": [
    "m00112"
  ]
}