{
  "errata_id": "71858f4073219313513e0e65049e5d9e5ee04e8bdb9f76bf97bf60136f810fc2",
  "attachments": [],
  "tags": [
    "lo:stax-cmath:02-03-03",
    "context-cnxmod:28231445-6e03-4384-b0a7-b58d8b92581c",
    "book:stax-cmath",
    "assignment-type:reading",
    "blooms:1",
    "time:medium",
    "book-slug:contemporary-mathematics",
    "module-slug:contemporary-mathematics:2-3-constructing-truth-tables"
  ],
  "books": [
    {
      "name": "stax-cmath",
      "lo": [
        "02-03-03"
      ]
    }
  ],
  "context": [
    "m00019"
  ]
}