{
  "errata_id": "af00c5864aa57268d97d592a1f24bb88d130707302825b98fb4acfbb9d88f012",
  "attachments": [],
  "tags": [
    "lo:stax-cmath:02-01-03",
    "context-cnxmod:63308aa6-1ca4-4025-b4ca-c9914d303b00",
    "book:stax-cmath",
    "assignment-type:reading",
    "blooms:1",
    "time:medium",
    "book-slug:contemporary-mathematics",
    "module-slug:contemporary-mathematics:2-1-statements-and-quantifiers"
  ],
  "books": [
    {
      "name": "stax-cmath",
      "lo": [
        "02-01-03"
      ]
    }
  ],
  "context": [
    "m00017"
  ]
}