{
  "errata_id": "65a3e16223b56f9f1bd484a039ba1d04b1f50bef36f5a17ab9ba88a427e84f45",
  "attachments": [],
  "tags": [
    "lo:stax-cmath:03-07-02",
    "book:stax-cmath",
    "assignment-type:reading",
    "blooms:1",
    "time:medium",
    "context-cnxmod:5cc525d7-a218-44ce-9183-5913f6238fae",
    "book-slug:contemporary-mathematics",
    "module-slug:contemporary-mathematics:3-7-clock-arithmetic"
  ],
  "books": [
    {
      "name": "stax-cmath",
      "lo": [
        "03-07-02"
      ]
    }
  ],
  "context": [
    "m00047"
  ]
}