{
  "errata_id": "438fb908352b722a3fdd4e28057d872289a2580b9b4c8370e40a3ff07c9ebb4b",
  "attachments": [],
  "tags": [
    "type:practice",
    "book:stax-cmath",
    "assignment-type:reading",
    "blooms:1",
    "time:medium",
    "context-cnxmod:792218eb-bd49-496b-983a-439f3697e6d0",
    "lo:stax-cmath:06-07-00",
    "book-slug:contemporary-mathematics",
    "module-slug:contemporary-mathematics:6-7-investments"
  ],
  "books": [
    {
      "name": "stax-cmath",
      "lo": [
        "06-07-00"
      ]
    }
  ],
  "context": [
    "m00063"
  ]
}