{
  "errata_id": "8b2dc50b9e36de32e20a3e5c0e71742c7c2e5ae14e3aeb697cb14db17dbe494a",
  "attachments": [],
  "tags": [
    "lo:stax-cmath:07-06-02",
    "book:stax-cmath",
    "assignment-type:reading",
    "blooms:1",
    "time:medium",
    "context-cnxmod:ef695a74-50c5-41a2-b843-0499142ba4ec",
    "book-slug:contemporary-mathematics",
    "module-slug:contemporary-mathematics:7-6-probability-with-permutations-and-combinations"
  ],
  "books": [
    {
      "name": "stax-cmath",
      "lo": [
        "07-06-02"
      ]
    }
  ],
  "context": [
    "m00090"
  ]
}