{
  "errata_id": "180cf44e43a5559b3d1653b2878335d4f8d5af9f1a331cb646020cafbb68cd4c",
  "attachments": [],
  "tags": [
    "lo:stax-cmath:06-11-01",
    "type:practice",
    "book:stax-cmath",
    "assignment-type:reading",
    "blooms:1",
    "time:medium",
    "context-cnxmod:15f6dedc-7cfc-4202-8fe2-3f019689c5f4",
    "book-slug:contemporary-mathematics",
    "module-slug:contemporary-mathematics:6-11-buying-or-leasing-a-car"
  ],
  "books": [
    {
      "name": "stax-cmath",
      "lo": [
        "06-11-01"
      ]
    }
  ],
  "context": [
    "m00067"
  ]
}