{
  "errata_id": "cb91faecc20dd0bb895d7831e8cbcad64e086662cfd06d3084136e587111ef51",
  "attachments": [],
  "tags": [
    "lo:stax-cmath:03-05-05",
    "book:stax-cmath",
    "assignment-type:reading",
    "blooms:1",
    "time:medium",
    "context-cnxmod:07a7fdac-a942-4c1d-b5f0-17ba2f835659",
    "book-slug:contemporary-mathematics",
    "module-slug:contemporary-mathematics:3-5-irrational-numbers"
  ],
  "books": [
    {
      "name": "stax-cmath",
      "lo": [
        "03-05-05"
      ]
    }
  ],
  "context": [
    "m00045"
  ]
}