{
  "errata_id": "7f3d8bfc507ef1e2de7120b1213a4b9ce2a843a9b2d983988aeebcccea984dff",
  "attachments": [],
  "tags": [
    "lo:stax-cmath:11-01-07",
    "context-cnxmod:91031584-74b3-4327-ad1f-f12f21835af9",
    "book:stax-cmath",
    "assignment-type:reading",
    "blooms:1",
    "time:medium",
    "book-slug:contemporary-mathematics",
    "module-slug:contemporary-mathematics:11-1-voting-methods"
  ],
  "books": [
    {
      "name": "stax-cmath",
      "lo": [
        "11-01-07"
      ]
    }
  ],
  "context": [
    "m00025"
  ]
}